cloudsnake/__init__.py
cloudsnake/__main__.py
cloudsnake/cli/cli.py
cloudsnake/cli/dto.py
cloudsnake/cli/rds.py
cloudsnake/cli/ssm.py
cloudsnake/cli/sso.py
cloudsnake/helpers.py
cloudsnake/logger.py
cloudsnake/sdk/aws.py
cloudsnake/sdk/ec2.py
cloudsnake/sdk/rds_session.py
cloudsnake/sdk/session.py
cloudsnake/sdk/ssm_parameters.py
cloudsnake/sdk/ssm_session.py
cloudsnake/sdk/sso.py
cloudsnake/sdk/sso_oidc.py
cloudsnake/styles/tui.tcss
cloudsnake/tui.py
cloudsnake/tui_v2.py
cloudsnake/utils.py
cloudsnake-0.9.1.dist-info/METADATA
cloudsnake-0.9.1.dist-info/WHEEL
cloudsnake-0.9.1.dist-info/entry_points.txt
cloudsnake-0.9.1.dist-info/licenses/LICENSE
cloudsnake-0.9.1.dist-info/RECORD
