Metadata-Version: 2.4
Name: cloudsnake
Version: 0.9.1
Summary: Some AWS CLI commands with a beautiful TUI
License: GPL-3.0
License-File: LICENSE
Keywords: aws,cli,rich,textual,cloudsnake
Author: containerscrew
Author-email: info@containerscrew.com
Requires-Python: >=3.12,<4.0
Classifier: Development Status :: 3 - Alpha
Classifier: Intended Audience :: End Users/Desktop
Classifier: License :: OSI Approved :: GNU General Public License v3 (GPLv3)
Classifier: Operating System :: MacOS
Classifier: Operating System :: POSIX :: Linux
Classifier: Programming Language :: Python
Classifier: Programming Language :: Python :: 3
Classifier: Programming Language :: Python :: 3.12
Classifier: Programming Language :: Python :: 3.13
Classifier: Programming Language :: Python :: 3.14
Classifier: Programming Language :: Python :: 3.10
Classifier: Programming Language :: Python :: 3.11
Classifier: Programming Language :: Python :: Implementation :: CPython
Classifier: Programming Language :: Python :: Implementation :: PyPy
Requires-Dist: boto3 (>=1.42.10,<2.0.0)
Requires-Dist: boto3-stubs (>=1.42.8,<1.43.0)
Requires-Dist: click (<8.4.0)
Requires-Dist: configparser (>=7.2.0,<8.0.0)
Requires-Dist: dacite (>=1.8.1,<2.0.0)
Requires-Dist: jmespath (>=1.0.1,<2.0.0)
Requires-Dist: moto (>=5.0.9,<6.0.0)
Requires-Dist: requests (>=2.32.5,<3.0.0)
Requires-Dist: rich (>=14.2.0,<15.0.0)
Requires-Dist: simple-term-menu (>=1.6.4,<2.0.0)
Requires-Dist: textual (>=7.2.0,<8.0.0)
Requires-Dist: typer (>=0.20,<0.22)
Requires-Dist: typing-extensions (>=4.12.0,<5.0.0)
Project-URL: Documentation, https://github.com/containerscrew/cloudsnake#readme
Project-URL: Repository, https://github.com/containerscrew/cloudsnake
